MANIFEST.in
VERSION
setup.py
libwebid/__init__.py
libwebid/package.json
libwebid/runlevel.py
libwebid.egg-info/PKG-INFO
libwebid.egg-info/SOURCES.txt
libwebid.egg-info/dependency_links.txt
libwebid.egg-info/entry_points.txt
libwebid.egg-info/requires.txt
libwebid.egg-info/top_level.txt
libwebid/canon/__init__.py
libwebid/canon/authenticationmethodreference.py
libwebid/canon/authorizationrequestdto.py
libwebid/canon/birthplaceidentityclaim.py
libwebid/canon/conflictingclaim.py
libwebid/canon/dateidentityclaim.py
libwebid/canon/documentedperson.py
libwebid/canon/fingerprint.py
libwebid/canon/fingerprintbrowser.py
libwebid/canon/fingerprintconfidence.py
libwebid/canon/fingerprintlocation.py
libwebid/canon/fingerprintlocationcity.py
libwebid/canon/fingerprintlocationcontinent.py
libwebid/canon/fingerprintlocationcountry.py
libwebid/canon/fingerprintref.py
libwebid/canon/fingerprintuseragent.py
libwebid/canon/genderidentityclaim.py
libwebid/canon/identificationartifacttype.py
libwebid/canon/identityclaim.py
libwebid/canon/identityclaimaggregate.py
libwebid/canon/identityclaimset.py
libwebid/canon/identityclaimtype.py
libwebid/canon/identitydocument.py
libwebid/canon/identitydocumenttype.py
libwebid/canon/integeridentityclaim.py
libwebid/canon/multinameidentityclaim.py
libwebid/canon/nameidentityclaim.py
libwebid/canon/ncnidentityclaim.py
libwebid/canon/oauthclientaccesstype.py
libwebid/canon/oauthclientdto.py
libwebid/canon/officialgivennamesclaim.py
libwebid/canon/sessionassertion.py
libwebid/canon/sessionclaims.py
libwebid/canon/sessiondto.py
libwebid/canon/sessionexists.py
libwebid/canon/sessionrequired.py
libwebid/canon/stringidentityclaim.py
libwebid/canon/subjectauthenticated.py
libwebid/canon/subjectclaimset.py
libwebid/canon/subjectef.py
libwebid/canon/subjectregistered.py
libwebid/canon/tokenconsumed.py
libwebid/canon/verifiedmailbox.py
libwebid/canon/api/__init__.py
libwebid/canon/api/documents/__init__.py
libwebid/canon/api/documents/retrievesessionresponse.py
libwebid/core/package.json
libwebid/domain/__init__.py
libwebid/domain/subject.py
libwebid/domain/repo/__init__.py
libwebid/domain/repo/session.py
libwebid/domain/repo/subject.py
