Metadata-Version: 2.1
Name: libwebid
Version: 0.53.0
Summary: Web Identity Common Library
Home-page: https://gitlab.com/unimatrixone
Author: Cochise Ruhulessin
Author-email: cochise.ruhulessin@unimatrixone.io
Classifier: Development Status :: 4 - Beta
Classifier: Environment :: Web Environment
Classifier: Intended Audience :: Developers
Classifier: Intended Audience :: Financial and Insurance Industry
Classifier: Intended Audience :: Healthcare Industry
Classifier: License :: Other/Proprietary License
Classifier: Programming Language :: Python :: 3.10
Classifier: Programming Language :: Python :: 3 :: Only
Classifier: Topic :: Internet
Classifier: Topic :: Internet :: WWW/HTTP :: Session
Classifier: Topic :: Security
Classifier: Topic :: Security :: Cryptography
Classifier: Topic :: Software Development :: Libraries
